deeplens_core_modules-0.0.1.dist-info/METADATA
deeplens_core_modules-0.0.1.dist-info/RECORD
deeplens_core_modules-0.0.1.dist-info/WHEEL
deeplens_core_modules-0.0.1.dist-info/top_level.txt
greengrass_common/__init__.py
greengrass_common/common_log_appender.py
greengrass_common/env_vars.py
greengrass_common/function_arn_fields.py
greengrass_common/greengrass_message.py
greengrass_common/local_cloudwatch_handler.py
greengrass_ipc_python_sdk/__init__.py
greengrass_ipc_python_sdk/ipc_client.py
greengrass_ipc_python_sdk/utils/__init__.py
greengrass_ipc_python_sdk/utils/exponential_backoff.py
greengrasssdk/IoTDataPlane.py
greengrasssdk/Lambda.py
greengrasssdk/__init__.py
greengrasssdk/client.py
greengrasssdk/utils/__init__.py
greengrasssdk/utils/testing.py
